strenum/__init__.py
strenum/__init__.pyi
strenum/_name_mangler.py
strenum/_name_mangler.pyi
strenum/_version.py
strenum/mixins.py
strenum/mixins.pyi
strenum/py.typed
StrEnum-0.4.14.dist-info/LICENSE
StrEnum-0.4.14.dist-info/METADATA
StrEnum-0.4.14.dist-info/WHEEL
StrEnum-0.4.14.dist-info/top_level.txt
StrEnum-0.4.14.dist-info/RECORD
